pyolin/__init__.py
pyolin/__main__.py
pyolin/core.py
pyolin/field.py
pyolin/header_detector.py
pyolin/ioformat.py
pyolin/parser.py
pyolin/pyolin.py
pyolin/record.py
pyolin/util.py
pyolin/plugins/__init__.py
pyolin/plugins/argv.py
pyolin/plugins/auto_parser.py
pyolin/plugins/json.py
pyolin/plugins/lines.py
pyolin/plugins/pip.py
pyolin/test/__init__.py
pyolin/test/conftest.py
pyolin/test/data_addresses.csv
pyolin/test/data_addresses_unix.csv
pyolin/test/data_addresses_with_header.csv
pyolin/test/data_amazon_reviews.tsv
pyolin/test/data_colors.json
pyolin/test/data_files.txt
pyolin/test/data_files_with_header.txt
pyolin/test/data_formatting.txt
pyolin/test/data_grades_simple_csv.csv
pyolin/test/data_grades_with_header.csv
pyolin/test/data_jq_example_rkm.json
pyolin/test/data_jq_example_twitter.jsonl
pyolin/test/data_json_example.json
pyolin/test/data_nba.txt
pyolin/test/data_news_decline.csv
pyolin/test/data_news_decline.tsv
pyolin/test/data_onerow.csv
pyolin/test/data_pickle
pyolin/test/test_awk_examples.py
pyolin/test/test_jq_examples.py
pyolin/test/test_json_finder.py
pyolin/test/test_plugin_pip.py
pyolin/test/test_pyolin.py
pyolin/test/test_recipes.py
pyolin-0.0.6.dist-info/METADATA
pyolin-0.0.6.dist-info/WHEEL
pyolin-0.0.6.dist-info/entry_points.txt
pyolin-0.0.6.dist-info/licenses/LICENSE
pyolin-0.0.6.dist-info/RECORD
