Metadata-Version: 2.4
Name: pyolin
Version: 0.0.6
Summary: Tool to easily write Python one-liners
Project-URL: Homepage, https://github.com/mauricelam/pyolin
Project-URL: Bug Tracker, https://github.com/mauricelam/pyolin/issues
Author-email: Maurice Lam <mauriceprograms@gmail.com>
License-File: LICENSE
Classifier: License :: OSI Approved :: Apache Software License
Classifier: Operating System :: OS Independent
Classifier: Programming Language :: Python :: 3
Requires-Python: >=3.8
Requires-Dist: hashbang>=0.1.14
Provides-Extra: dev
Requires-Dist: pandas; extra == 'dev'
Requires-Dist: pytest; extra == 'dev'
